mask_cmd-1.0.0.dist-info/METADATA
mask_cmd-1.0.0.dist-info/WHEEL
mask_cmd-1.0.0.dist-info/entry_points.txt
mask_cmd/__init__.py
mask_cmd/call.py
mask_cmd/cmd.py
mask_cmd-1.0.0.dist-info/RECORD
