Metadata-Version: 2.1
Name: mask_cmd
Version: 1.0.0
Summary: Default template for PDM package
Author-Email: mask <whitecapella@naver.com>
License: MIT
Project-URL: Homepage, https://pypi.org/project/mask_cmd/
Project-URL: Issue, https://github.com/WhiteCapella/mask_cmd/issues
Requires-Python: >=3.9
Requires-Dist: mask-plus>=1.0.0
Requires-Dist: mask-divide>=1.0.0
Requires-Dist: mask-times>=1.0.0
